<annotation verified="yes">
	<folder>frames</folder>
	<filename>Coldplay_-_The_Scientist_(Piano_Cover)-IjfocYTF9EQ.mp4_4088.jpg</filename>
	<path>D:\dev\research\piano-fingering-extraction\components\hand_dataset\frames\Coldplay_-_The_Scientist_(Piano_Cover)-IjfocYTF9EQ.mp4_4088.jpg</path>
	<source>
		<database>Unknown</database>
	</source>
	<size>
		<width>1920</width>
		<height>1080</height>
		<depth>3</depth>
	</size>
	<segmented>0</segmented>
	<object>
		<name>left</name>
		<pose>Unspecified</pose>
		<truncated>0</truncated>
		<difficult>0</difficult>
		<bndbox>
			<xmin>186</xmin>
			<ymin>627</ymin>
			<xmax>459</xmax>
			<ymax>903</ymax>
		</bndbox>
	</object>
	<object>
		<name>right</name>
		<pose>Unspecified</pose>
		<truncated>0</truncated>
		<difficult>0</difficult>
		<bndbox>
			<xmin>850</xmin>
			<ymin>669</ymin>
			<xmax>1097</xmax>
			<ymax>916</ymax>
		</bndbox>
	</object>
</annotation>
