<annotation verified="yes">
	<folder>frames</folder>
	<filename>Descendants_of_Shinobi_-_Final_Fantasy_VII_Piano_Collections_[Advanced]-L1V-iD3LBrI.webm_4185.jpg</filename>
	<path>D:\dev\research\piano-fingering-extraction\components\hand_dataset\frames\Descendants_of_Shinobi_-_Final_Fantasy_VII_Piano_Collections_[Advanced]-L1V-iD3LBrI.webm_4185.jpg</path>
	<source>
		<database>Unknown</database>
	</source>
	<size>
		<width>1920</width>
		<height>1080</height>
		<depth>3</depth>
	</size>
	<segmented>0</segmented>
	<object>
		<name>left</name>
		<pose>Unspecified</pose>
		<truncated>0</truncated>
		<difficult>0</difficult>
		<bndbox>
			<xmin>502</xmin>
			<ymin>659</ymin>
			<xmax>802</xmax>
			<ymax>977</ymax>
		</bndbox>
	</object>
	<object>
		<name>right</name>
		<pose>Unspecified</pose>
		<truncated>0</truncated>
		<difficult>0</difficult>
		<bndbox>
			<xmin>879</xmin>
			<ymin>645</ymin>
			<xmax>1089</xmax>
			<ymax>948</ymax>
		</bndbox>
	</object>
</annotation>
