<annotation verified="yes">
	<folder>frames</folder>
	<filename>Kirby_Piano_Medley_(Gourmet_Race_&amp;_King_Dedede)_[Intermediate]_+_sheets-IQRRfNJUTtw.webm_4338.jpg</filename>
	<path>D:\dev\research\piano-fingering-extraction\components\hand_dataset\frames\Kirby_Piano_Medley_(Gourmet_Race_&amp;_King_Dedede)_[Intermediate]_+_sheets-IQRRfNJUTtw.webm_4338.jpg</path>
	<source>
		<database>Unknown</database>
	</source>
	<size>
		<width>854</width>
		<height>480</height>
		<depth>3</depth>
	</size>
	<segmented>0</segmented>
	<object>
		<name>left</name>
		<pose>Unspecified</pose>
		<truncated>1</truncated>
		<difficult>0</difficult>
		<bndbox>
			<xmin>249</xmin>
			<ymin>317</ymin>
			<xmax>431</xmax>
			<ymax>480</ymax>
		</bndbox>
	</object>
	<object>
		<name>right</name>
		<pose>Unspecified</pose>
		<truncated>1</truncated>
		<difficult>0</difficult>
		<bndbox>
			<xmin>503</xmin>
			<ymin>338</ymin>
			<xmax>622</xmax>
			<ymax>480</ymax>
		</bndbox>
	</object>
</annotation>
