<annotation verified="yes">
	<folder>frames</folder>
	<filename>Lana_Del_Rey_-_Summertime_Sadness___Piano_cover-aqO7WydN70Q.mkv_741.jpg</filename>
	<path>D:\dev\research\piano-fingering-extraction\components\hand_dataset\frames\Lana_Del_Rey_-_Summertime_Sadness___Piano_cover-aqO7WydN70Q.mkv_741.jpg</path>
	<source>
		<database>Unknown</database>
	</source>
	<size>
		<width>1920</width>
		<height>1080</height>
		<depth>3</depth>
	</size>
	<segmented>0</segmented>
	<object>
		<name>left</name>
		<pose>Unspecified</pose>
		<truncated>1</truncated>
		<difficult>0</difficult>
		<bndbox>
			<xmin>338</xmin>
			<ymin>760</ymin>
			<xmax>622</xmax>
			<ymax>1080</ymax>
		</bndbox>
	</object>
	<object>
		<name>right</name>
		<pose>Unspecified</pose>
		<truncated>1</truncated>
		<difficult>0</difficult>
		<bndbox>
			<xmin>890</xmin>
			<ymin>740</ymin>
			<xmax>1100</xmax>
			<ymax>1080</ymax>
		</bndbox>
	</object>
</annotation>
